data_structures/__init__.py
data_structures/array.py
data_structures/graph.py
data_structures/linked_list.py
data_structures/queue.py
data_structures/stack.py
data_structures/tree.py
tahar_data_structure-0.1.0.dist-info/licenses/LICENSE
tahar_data_structure-0.1.0.dist-info/METADATA
tahar_data_structure-0.1.0.dist-info/WHEEL
tahar_data_structure-0.1.0.dist-info/top_level.txt
tahar_data_structure-0.1.0.dist-info/RECORD
