Metadata-Version: 2.4
Name: tahar-data-structure
Version: 0.1.0
Summary: Data Structures
Author-email: Djaloud <tdjaloud@aimsammi.org>
License: MIT
Project-URL: Homepage, https://github.com/djaloud94/data-structures-python.git
Project-URL: Documentation, https://djaloud94.github.io/data-structures-python
Keywords: Array,Stack,Tree
Classifier: Programming Language :: Python :: 3
Classifier: License :: OSI Approved :: MIT License
Requires-Python: >=3.8
License-File: LICENSE
Dynamic: license-file
